Ufd/Ufd.py
Ufd/__init__.py
Ufd/disk.gif
Ufd/file.gif
Ufd/folder.gif
Ufd/icon.ico
Ufd-1.0.0.dist-info/LICENSE.txt
Ufd-1.0.0.dist-info/METADATA
Ufd-1.0.0.dist-info/WHEEL
Ufd-1.0.0.dist-info/top_level.txt
Ufd-1.0.0.dist-info/RECORD
