Metadata-Version: 2.1
Name: Ufd
Version: 1.0.0
Summary: Unopinionated, minimalist, reusable, slightly configurable, general-purpose file-dialog.
Home-page: https://github.com/emboiko/Ufd
Author: Emboiko
Author-email: ed@emboiko.com
License: UNKNOWN
Keywords: single instance
Platform: UNKNOWN
Classifier: Programming Language :: Python :: 3
Classifier: Programming Language :: Python :: 3.7
Classifier: Programming Language :: Python :: 3.8
Classifier: Programming Language :: Python :: 3.9
Classifier: License :: OSI Approved :: MIT License
Classifier: Operating System :: Microsoft :: Windows
